robinhood_portfolio_manager/Robinhood.py
robinhood_portfolio_manager/__init__.py
robinhood_portfolio_manager-0.0b10.dist-info/LICENSE
robinhood_portfolio_manager-0.0b10.dist-info/METADATA
robinhood_portfolio_manager-0.0b10.dist-info/WHEEL
robinhood_portfolio_manager-0.0b10.dist-info/entry_points.txt
robinhood_portfolio_manager-0.0b10.dist-info/top_level.txt
robinhood_portfolio_manager-0.0b10.dist-info/RECORD
