Metadata-Version: 2.1
Name: robinhood-portfolio-manager
Version: 0.0b10
Summary: A portfolio manager for Robinhood
Home-page: https://github.com/MinaMessiah/robinhood_portfolio_manager
Author: Mina Messiah
Author-email: mena.sb.109@gmail.com
License: MIT License
Platform: UNKNOWN
Classifier: Programming Language :: Python :: 3
Classifier: License :: OSI Approved :: MIT License
Classifier: Operating System :: OS Independent
Requires-Python: >=3.6
Requires-Dist: pyotp
Requires-Dist: openpyxl
Requires-Dist: robin-stocks
